ctrl4bi/__init__.py
ctrl4bi/aws_connect.py
ctrl4bi/cleanser.py
ctrl4bi/data_wrangling.py
ctrl4bi/datasets.py
ctrl4bi/etl_testing.py
ctrl4bi/exceptions.py
ctrl4bi-1.0.5.dist-info/LICENSE
ctrl4bi-1.0.5.dist-info/METADATA
ctrl4bi-1.0.5.dist-info/WHEEL
ctrl4bi-1.0.5.dist-info/top_level.txt
ctrl4bi-1.0.5.dist-info/RECORD
