Metadata-Version: 2.1
Name: ctrl4bi
Version: 1.0.5
Summary: A helper package for Business Intelligence solutions
Home-page: https://github.com/vkreat-tech/ctrl4bi
Author: Shaji James
Author-email: shajijames7@gmail.com
Classifier: Programming Language :: Python :: 3
Classifier: License :: OSI Approved :: MIT License
Classifier: Operating System :: OS Independent
Requires-Python: >=3.6
License-File: LICENSE
